eaas/__init__.py
eaas/async_client.py
eaas/client.py
eaas/config.py
eaas/eaas_cli.py
eaas/endpoint.py
eaas/metrics.py
eaas/statistics/__init__.py
eaas/statistics/ci.py
eaas/visualization/__init__.py
tests/__init__.py
tests/test_api.py
tests/test_async.py
eaas-0.3.10.dist-info/LICENSE
eaas-0.3.10.dist-info/METADATA
eaas-0.3.10.dist-info/WHEEL
eaas-0.3.10.dist-info/entry_points.txt
eaas-0.3.10.dist-info/top_level.txt
eaas-0.3.10.dist-info/RECORD
