Metadata-Version: 2.1
Name: eaas
Version: 0.3.10
Summary: Evaluation as a Service for Natural Language Processing
Home-page: https://github.com/inspired-co/eaas_client
Author: Inspired Cognition
License: Apache 2.0
Platform: UNKNOWN
Classifier: Intended Audience :: Developers
Classifier: Topic :: Text Processing
Classifier: Topic :: Scientific/Engineering :: Artificial Intelligence
Classifier: License :: OSI Approved :: Apache Software License
Classifier: Programming Language :: Python :: 3
License-File: LICENSE
Requires-Dist: nltk (>=3.2)
Requires-Dist: numpy
Requires-Dist: scipy
Requires-Dist: matplotlib
Requires-Dist: scikit-learn
Requires-Dist: pandas
Requires-Dist: tqdm
Requires-Dist: requests
